pulumi_select/__main__.py
pulumi_select-0.1.3.dist-info/LICENCE.txt
pulumi_select-0.1.3.dist-info/METADATA
pulumi_select-0.1.3.dist-info/WHEEL
pulumi_select-0.1.3.dist-info/entry_points.txt
pulumi_select-0.1.3.dist-info/top_level.txt
pulumi_select-0.1.3.dist-info/RECORD
